{"cardiovascular_disease": ["treatment", "study", "placebo", "group", "blood", "insulin", "significantly", "dose", "effect", "pressure"], "chronic_kidney_disease": ["study", "mortality", "data", "risk", "clinical", "coronary", "stroke", "acute", "analysis", "hospital"], "mental_disorder": ["study", "group", "risk", "pain", "bone", "significant", "age", "associated", "knee", "training"], "musculoskeletal_disorder": ["study", "group", "cancer", "surgery", "clinical", "treatment", "time", "analysis", "risk", "prostate"], "neoplasm": ["study", "treatment", "group", "intervention", "care", "trial", "health", "control", "use", "randomized"], "neurological_disorder": ["treatment", "study", "cancer", "dose", "response", "therapy", "disease", "cell", "survival", "hiv"]}